tests/__init__.py
tests/test_binance_clients.py
tests/test_binance_crypto.py
tests/test_binance_utils.py
xchainpy_binance/__init__.py
xchainpy_binance/client.py
xchainpy_binance/crypto.py
xchainpy_binance/utils.py
xchainpy_binance/models/__init__.py
xchainpy_binance/models/balance.py
xchainpy_binance/models/coin.py
xchainpy_binance/models/fee.py
xchainpy_binance/models/multi_transfer.py
xchainpy_binance-0.2.3.dist-info/LICENSE
xchainpy_binance-0.2.3.dist-info/METADATA
xchainpy_binance-0.2.3.dist-info/WHEEL
xchainpy_binance-0.2.3.dist-info/top_level.txt
xchainpy_binance-0.2.3.dist-info/RECORD
