Metadata-Version: 2.1
Name: xchainpy-binance
Version: 0.2.3
Summary: Custom Binance client and utilities used by XChainPY clients
Home-page: https://github.com/xchainjs/xchainpy-lib/tree/main/xchainpy/xchainpy_binance
Author: THORChain
Author-email: 
License: MIT
Keywords: BNB,Binance,XChainpy_binance,THORChain
Platform: UNKNOWN
Classifier: Intended Audience :: Developers
Classifier: Topic :: Software Development :: Libraries :: Python Modules
Classifier: License :: OSI Approved :: MIT License
Classifier: Programming Language :: Python :: 3
Classifier: Programming Language :: Python :: 3.9
Classifier: Programming Language :: Python
License-File: LICENSE
Requires-Dist: py-binance-chain (>=0.2)
Requires-Dist: xchainpy-client (>=0.1.6)
Requires-Dist: xchainpy-crypto (>=0.1.7)
Requires-Dist: xchainpy-util (>=0.1.8)
